ExpressIntegrations/__init__.py
ExpressIntegrations/Acuity/__init__.py
ExpressIntegrations/Acuity/acuity.py
ExpressIntegrations/Emerge/__init__.py
ExpressIntegrations/Emerge/emerge.py
ExpressIntegrations/GMail/__init__.py
ExpressIntegrations/GMail/gmail.py
ExpressIntegrations/HTTP/Requests.py
ExpressIntegrations/HTTP/__init__.py
ExpressIntegrations/HubSpot/HSUtils.py
ExpressIntegrations/HubSpot/__init__.py
ExpressIntegrations/HubSpot/associations.py
ExpressIntegrations/HubSpot/companies.py
ExpressIntegrations/HubSpot/constants.py
ExpressIntegrations/HubSpot/contacts.py
ExpressIntegrations/HubSpot/deals.py
ExpressIntegrations/HubSpot/engagements.py
ExpressIntegrations/HubSpot/hubspot.py
ExpressIntegrations/HubSpot/lineitems.py
ExpressIntegrations/HubSpot/object_properties.py
ExpressIntegrations/HubSpot/owners.py
ExpressIntegrations/HubSpot/products.py
ExpressIntegrations/MailChimp/__init__.py
ExpressIntegrations/MailChimp/mailchimp.py
ExpressIntegrations/ManagedMissions/__init__.py
ExpressIntegrations/ManagedMissions/managed_missions.py
ExpressIntegrations/MinistryPlatform/__init__.py
ExpressIntegrations/MinistryPlatform/ministry.py
ExpressIntegrations/Monday/__init__.py
ExpressIntegrations/Monday/monday.py
ExpressIntegrations/NorthText/__init__.py
ExpressIntegrations/NorthText/northtext.py
ExpressIntegrations/RingCentral/__init__.py
ExpressIntegrations/RingCentral/ringcentral.py
ExpressIntegrations/TriNet/__init__.py
ExpressIntegrations/TriNet/trinet.py
ExpressIntegrations/Utils/AsyncUtils.py
ExpressIntegrations/Utils/Utils.py
ExpressIntegrations/Utils/__init__.py
ExpressIntegrations/Utils/async.py
ExpressIntegrations/Zoho/__init__.py
ExpressIntegrations/Zoho/contacts.py
ExpressIntegrations/Zoho/customerpayments.py
ExpressIntegrations/Zoho/expenses.py
ExpressIntegrations/Zoho/invoices.py
ExpressIntegrations/Zoho/items.py
ExpressIntegrations/Zoho/users.py
ExpressIntegrations/Zoho/zoho.py
HTTP/Requests.py
HTTP/__init__.py
HubSpot/HSUtils.py
HubSpot/__init__.py
expressintegrations-1.4.9.dist-info/LICENSE
expressintegrations-1.4.9.dist-info/METADATA
expressintegrations-1.4.9.dist-info/WHEEL
expressintegrations-1.4.9.dist-info/top_level.txt
expressintegrations-1.4.9.dist-info/RECORD
