Metadata-Version: 2.1
Name: expressintegrations
Version: 1.4.9
Summary: Custom Utilities for the Express Integrations platform
Home-page: https://github.com/pypa/expressintegrations
Author: Express Integrations
Author-email: express.integrations@gmail.com
License: UNKNOWN
Platform: UNKNOWN
Classifier: Programming Language :: Python :: 3
Classifier: License :: OSI Approved :: MIT License
Classifier: Operating System :: OS Independent
Requires-Python: >=3.6
License-File: LICENSE
